leaf/__init__.py
leaf/cli.py
leaf_cli-0.0.1.dist-info/LICENSE
leaf_cli-0.0.1.dist-info/METADATA
leaf_cli-0.0.1.dist-info/WHEEL
leaf_cli-0.0.1.dist-info/entry_points.txt
leaf_cli-0.0.1.dist-info/top_level.txt
leaf_cli-0.0.1.dist-info/RECORD
